fish/__init__.py
fish/main.py
test_fish-0.0.2.dist-info/METADATA
test_fish-0.0.2.dist-info/WHEEL
test_fish-0.0.2.dist-info/top_level.txt
test_fish-0.0.2.dist-info/RECORD
